pystockfilter/__init__.py
pystockfilter/backtesting/__init__.py
pystockfilter/backtesting/_plotting.py
pystockfilter/backtesting/_stats.py
pystockfilter/backtesting/_util.py
pystockfilter/backtesting/_version.py
pystockfilter/backtesting/autoscale_cb.js
pystockfilter/backtesting/backtesting.py
pystockfilter/backtesting/lib.py
pystockfilter/base/__init__.py
pystockfilter/base/base_helper.py
pystockfilter/data/__init__.py
pystockfilter/data/local_source.py
pystockfilter/data/pystockdb_source.py
pystockfilter/data/stock_data_source.py
pystockfilter/data/yfinance_source.py
pystockfilter/data/yfinance_source_cache.py
pystockfilter/strategy/__init__.py
pystockfilter/strategy/atr_strategy.py
pystockfilter/strategy/base_strategy.py
pystockfilter/strategy/bollinger_volume_strategy.py
pystockfilter/strategy/doji_rsi_strategy.py
pystockfilter/strategy/ema_cross_close_strategy.py
pystockfilter/strategy/ema_cross_ema_strategy.py
pystockfilter/strategy/ema_cross_sma_strategy.py
pystockfilter/strategy/macd_strategy.py
pystockfilter/strategy/moving_average_rsi_strategy.py
pystockfilter/strategy/rsi_strategy.py
pystockfilter/strategy/sma_cross_close_strategy.py
pystockfilter/strategy/sma_cross_sma_strategy.py
pystockfilter/strategy/uo_ema_cross_close_strategy.py
pystockfilter/strategy/uo_ema_cross_ema_strategy.py
pystockfilter/strategy/uo_strategy.py
pystockfilter/tool/__init__.py
pystockfilter/tool/chunked_optimizer.py
pystockfilter/tool/helper.py
pystockfilter/tool/result.py
pystockfilter/tool/start_backtest.py
pystockfilter/tool/start_base.py
pystockfilter/tool/start_batch_optimizer.py
pystockfilter/tool/start_chunked_optimizer.py
pystockfilter/tool/start_optimizer.py
pystockfilter/tool/start_seq_optimizer.py
pystockfilter-2.3.1.dist-info/LICENSE
pystockfilter-2.3.1.dist-info/METADATA
pystockfilter-2.3.1.dist-info/WHEEL
pystockfilter-2.3.1.dist-info/RECORD
