Metadata-Version: 2.1
Name: pystockfilter
Version: 2.3.1
Summary: Intelligent Stock Screening for Informed Investment Decisions
License: MIT
Author: SlashGordon
Author-email: slash.gordon.dev@gmail.com
Requires-Python: >=3.11,<4.0
Classifier: License :: OSI Approved :: MIT License
Classifier: Programming Language :: Python :: 3
Classifier: Programming Language :: Python :: 3.11
Classifier: Programming Language :: Python :: 3.12
Classifier: Programming Language :: Python :: 3.13
Requires-Dist: bokeh (>=2.0.0,<3.0.0)
Requires-Dist: joblib (>=1.4.2,<2.0.0)
Requires-Dist: numpy (>=1.17.0,<2.0.0)
Requires-Dist: pandas (>=2.1.0,<3.0.0)
Requires-Dist: pandas-ta (>=0.3.14b0,<0.4.0)
Requires-Dist: pystockdb (>=1.2.0,<2.0.0)
Requires-Dist: python-dateutil (>=2.8.2,<3.0.0)
Requires-Dist: scikit-optimize (>=0.10.2,<0.11.0)
Requires-Dist: setuptools (>=75.2.0,<76.0.0)
Requires-Dist: yfinance (==0.2.46)
